django_spaday/__init__.py
django_spaday/apps.py
django_spaday/models.py
django_spaday/settings.py
django_spaday/urls.py
django_spaday/utils.py
django_spaday/views.py
django_spaday/api/__init__.py
django_spaday/api/pagination.py
django_spaday/api/permissions.py
django_spaday/api/renderers.py
django_spaday/api/urls.py
django_spaday/api/utils.py
django_spaday/api/views.py
django_spaday/api/viewsets.py
django_spaday/api/serializers/__init__.py
django_spaday/api/serializers/auditlog.py
django_spaday/api/serializers/auth.py
django_spaday/api/serializers/deleted.py
django_spaday/api/serializers/django_celery_results.py
django_spaday/api/serializers/filters.py
django_spaday/management/__init__.py
django_spaday/management/commands/__init__.py
django_spaday/management/commands/export_perms.py
django_spaday/migrations/0001_initial.py
django_spaday/migrations/__init__.py
django_spaday/templates/includes/favicons.html
django_spaday/templates/spaday/vue.html
django_spaday-0.1.4.dist-info/AUTHORS.md
django_spaday-0.1.4.dist-info/LICENSE
django_spaday-0.1.4.dist-info/METADATA
django_spaday-0.1.4.dist-info/WHEEL
django_spaday-0.1.4.dist-info/top_level.txt
django_spaday-0.1.4.dist-info/RECORD
