Metadata-Version: 2.2
Name: django-spaday
Version: 0.1.4
Summary: A Django package that provides 'out-of-the-box' JWT auth, user, group, and permission APIs for use in Single Page Apps (eg - Vue, React).
Author-email: Tim Santor <tsantor@xstudios.com>
Project-URL: Repository, https://github.com/tsantor/django-spaday.git
Project-URL: Issues, https://github.com/tsantor/django-spaday/issues
Project-URL: Changelog, https://github.com/tsantor/django-spaday/blob/master/HISTORY.md
Classifier: Development Status :: 5 - Production/Stable
Classifier: Intended Audience :: Developers
Classifier: Natural Language :: English
Classifier: Programming Language :: Python :: 3.9
Classifier: Programming Language :: Python :: 3.10
Classifier: Programming Language :: Python :: 3.11
Classifier: Programming Language :: Python :: 3.12
Requires-Python: >=3.9
License-File: LICENSE
License-File: AUTHORS.md
Requires-Dist: django<5.0,>=4.0
Requires-Dist: drf-spectacular
Requires-Dist: django-auditlog
Requires-Dist: django-celery-results
Requires-Dist: django-filter
Requires-Dist: django-perm-filter
Provides-Extra: dev
